complex_parser/__init__.py
complex_parser/main.py
complex_parser-0.0.2.dist-info/METADATA
complex_parser-0.0.2.dist-info/WHEEL
complex_parser-0.0.2.dist-info/top_level.txt
complex_parser-0.0.2.dist-info/RECORD
