Metadata-Version: 2.1
Name: complex-parser
Version: 0.0.2
Summary: A versatile Python package for data extraction from JSON-like structures with user-defined format keys, enhanced with synonym retrieval capabilities.
Home-page: https://github.com/The-Nebula-Developers/Complex-Parser
Author: The Nebula Developer
Author-email: support@nebuladevs.tech
License: Mozilla Public License Version 2.0
Keywords: python,data,parsing,json,complex,synonyms,similar,custom parsing,data parser,synomym data parser,keyword extractor,fuzzywuzzy,nltk,words,json data
Classifier: Programming Language :: Python :: 3
Classifier: Operating System :: OS Independent
Requires-Python: >=3.10
Requires-Dist: fuzzywuzzy >=0.18.0
Requires-Dist: nltk >=3.6.2
Requires-Dist: psutil
Provides-Extra: dev
Requires-Dist: twine ; extra == 'dev'
